CHANGELOG.md
LICENSE
README.md
ramka/__init__.py
ramka/app.py
ramka/middleware/__init__.py
ramka/middleware/base_middleware.py
ramka/request/__init__.py
ramka/request/request.py
ramka/response/__init__.py
ramka/response/response.py
ramka/routing/__init__.py
ramka/routing/route.py
ramka/routing/router.py
ramka/static/__init__.py
ramka/static/engine.py
ramka/templates/__init__.py
ramka/templates/engine.py
ramka/test/__init__.py
ramka/test/session.py
ramka/views/__init__.py
ramka/views/base_view.py
ramka/views/errors.py
ramka-0.1.2.dist-info/LICENSE
ramka-0.1.2.dist-info/WHEEL
ramka-0.1.2.dist-info/METADATA
ramka-0.1.2.dist-info/RECORD
