Metadata-Version: 2.1
Name: ramka
Version: 0.1.2
Summary: ramka - a simple Python web framework
Home-page: https://github.com/mateuszcisek/ramka
License: MIT
Keywords: web,framework,wsgi
Author: Mateusz Cisek
Author-email: cismat@gmail.com
Requires-Python: >=3.9,<4.0
Classifier: Environment :: Web Environment
Classifier: Intended Audience :: Developers
Classifier: License :: OSI Approved :: MIT License
Classifier: Operating System :: OS Independent
Classifier: Programming Language :: Python
Classifier: Programming Language :: Python :: 3
Classifier: Programming Language :: Python :: 3 :: Only
Classifier: Programming Language :: Python :: 3.10
Classifier: Programming Language :: Python :: 3.9
Classifier: Topic :: Internet :: WWW/HTTP
Classifier: Topic :: Software Development :: Libraries :: Application Frameworks
Classifier: Topic :: Software Development :: Libraries :: Python Modules
Requires-Dist: Jinja2 (>=3.1.2,<4.0.0)
Requires-Dist: WebOb (>=1.8.7,<2.0.0)
Requires-Dist: furo (>=2022.4.7,<2023.0.0)
Requires-Dist: gunicorn (>=20.1.0,<21.0.0)
Requires-Dist: parse (>=1.19.0,<2.0.0)
Requires-Dist: requests (>=2.27.1,<3.0.0)
Requires-Dist: whitenoise (>=6.0.0,<7.0.0)
Project-URL: Bug Tracker, https://github.com/mateuszcisek/ramka/issues
Project-URL: Repository, https://github.com/mateuszcisek/ramka
